quditto_node/__init__.py
quditto_node/backend.py
quditto_node/configuration.py
quditto_node/database.py
quditto_node/grpc_serialization/__init__.py
quditto_node/grpc_serialization/interfaces_pb2.py
quditto_node/grpc_serialization/interfaces_pb2_grpc.py
quditto_node/key_management.py
quditto_node/key_synchronization.py
quditto_node/main.py
quditto_node-0.1.8.dist-info/METADATA
quditto_node-0.1.8.dist-info/WHEEL
quditto_node-0.1.8.dist-info/entry_points.txt
quditto_node-0.1.8.dist-info/RECORD
