Metadata-Version: 2.1
Name: quditto_node
Version: 0.1.8
Summary: Software for quditto node
Author: rmcelaya
Author-email: rmcelaya@protonmail.com
Classifier: Programming Language :: Python :: 2
Classifier: Programming Language :: Python :: 2.7
Classifier: Programming Language :: Python :: 3
Classifier: Programming Language :: Python :: 3.4
Classifier: Programming Language :: Python :: 3.5
Classifier: Programming Language :: Python :: 3.6
Classifier: Programming Language :: Python :: 3.7
Classifier: Programming Language :: Python :: 3.8
Classifier: Programming Language :: Python :: 3.9
Classifier: Programming Language :: Python :: 3.10
Classifier: Programming Language :: Python :: 3.11
Classifier: Programming Language :: Python :: 3.12
Requires-Dist: aioconsole (==0.3.3)
Requires-Dist: bitarray (==2.8.1)
Requires-Dist: grpcio (==1.48.2)
Requires-Dist: protobuf (==3.19.6)
Requires-Dist: python-daemon (==2.3.2)
Requires-Dist: simulaqron (==3.0.16)
